{"links":[{"id":4,"source":132,"target":4,"value":0.07094375,"lineStyle":{"width":0.29188749999999997,"color":"#f89f9a"},"symbolSize":0.7094374999999999},{"id":5,"source":132,"target":5,"value":0.048087500000000005,"lineStyle":{"width":0.246175,"color":"#f89f9a"},"symbolSize":0.48087500000000005},{"id":6,"source":132,"target":6,"value":0.059006249999999996,"lineStyle":{"width":0.2680125,"color":"#f89f9a"},"symbolSize":0.5900624999999999},{"id":12,"source":132,"target":12,"value":0.04916875,"lineStyle":{"width":0.2483375,"color":"#f89f9a"},"symbolSize":0.49168749999999994},{"id":13,"source":132,"target":13,"value":0.06073749999999999,"lineStyle":{"width":0.27147499999999997,"color":"#f89f9a"},"symbolSize":0.6073749999999999},{"id":14,"source":132,"target":14,"value":0.04921249999999999,"lineStyle":{"width":0.24842499999999998,"color":"#f89f9a"},"symbolSize":0.4921249999999999},{"id":17,"source":132,"target":17,"value":0.0393125,"lineStyle":{"width":0.228625,"color":"#f89f9a"},"symbolSize":0.393125},{"id":18,"source":132,"target":18,"value":0.04518124999999999,"lineStyle":{"width":0.24036249999999998,"color":"#f89f9a"},"symbolSize":0.45181249999999995},{"id":19,"source":132,"target":19,"value":0.04824375,"lineStyle":{"width":0.2464875,"color":"#f89f9a"},"symbolSize":0.4824375},{"id":35,"source":132,"target":35,"value":0.05588750000000001,"lineStyle":{"width":0.261775,"color":"#f89f9a"},"symbolSize":0.558875},{"id":71,"source":132,"target":71,"value":0.04051875,"lineStyle":{"width":0.2310375,"color":"#f89f9a"},"symbolSize":0.4051875},{"id":80,"source":132,"target":80,"value":-0.047150000000000004,"lineStyle":{"width":0.24430000000000002,"color":"#8dc5f8"},"symbolSize":-0.47150000000000003},{"id":90,"source":132,"target":90,"value":-0.029925,"lineStyle":{"width":0.20984999999999998,"color":"#8dc5f8"},"symbolSize":-0.29925},{"id":109,"source":132,"target":109,"value":0.0364,"lineStyle":{"width":0.2228,"color":"#f89f9a"},"symbolSize":0.364},{"id":112,"source":132,"target":112,"value":0.042725,"lineStyle":{"width":0.23545,"color":"#f89f9a"},"symbolSize":0.42725},{"id":113,"source":132,"target":113,"value":0.057912500000000006,"lineStyle":{"width":0.265825,"color":"#f89f9a"},"symbolSize":0.5791250000000001},{"id":114,"source":132,"target":114,"value":0.07928125,"lineStyle":{"width":0.30856249999999996,"color":"#f89f9a"},"symbolSize":0.7928124999999999},{"id":115,"source":132,"target":115,"value":0.11523749999999999,"lineStyle":{"width":0.380475,"color":"#f89f9a"},"symbolSize":1.152375},{"id":117,"source":132,"target":117,"value":0.0812,"lineStyle":{"width":0.3124,"color":"#f89f9a"},"symbolSize":0.8119999999999999},{"id":124,"source":132,"target":124,"value":0.03816875,"lineStyle":{"width":0.2263375,"color":"#f89f9a"},"symbolSize":0.3816875},{"id":129,"source":132,"target":129,"value":0.07876250000000001,"lineStyle":{"width":0.30752500000000005,"color":"#f89f9a"},"symbolSize":0.7876250000000001},{"id":130,"source":132,"target":130,"value":0.45168125000000003,"lineStyle":{"width":1.0533625,"color":"#f89f9a"},"symbolSize":4.5168125},{"id":131,"source":132,"target":131,"value":0.44629375,"lineStyle":{"width":1.0425875,"color":"#f89f9a"},"symbolSize":4.4629375},{"id":141,"source":132,"target":141,"value":0.046799999999999994,"lineStyle":{"width":0.24359999999999998,"color":"#f89f9a"},"symbolSize":0.46799999999999997},{"id":142,"source":132,"target":142,"value":0.11240625000000001,"lineStyle":{"width":0.3748125,"color":"#f89f9a"},"symbolSize":1.1240625000000002},{"id":144,"source":132,"target":144,"value":0.10546250000000001,"lineStyle":{"width":0.36092500000000005,"color":"#f89f9a"},"symbolSize":1.0546250000000001},{"id":148,"source":132,"target":148,"value":0.04505625,"lineStyle":{"width":0.2401125,"color":"#f89f9a"},"symbolSize":0.4505625}]}