{"links":[{"id":5,"source":82,"target":5,"value":0.0443625,"lineStyle":{"width":0.238725,"color":"#f89f9a"},"symbolSize":0.443625},{"id":75,"source":82,"target":75,"value":0.053518750000000004,"lineStyle":{"width":0.25703750000000003,"color":"#f89f9a"},"symbolSize":0.5351875},{"id":80,"source":82,"target":80,"value":0.0729,"lineStyle":{"width":0.2958,"color":"#f89f9a"},"symbolSize":0.7290000000000001},{"id":81,"source":82,"target":81,"value":0.20014375,"lineStyle":{"width":0.5502875,"color":"#f89f9a"},"symbolSize":2.0014375},{"id":83,"source":82,"target":83,"value":0.16759999999999997,"lineStyle":{"width":0.48519999999999996,"color":"#f89f9a"},"symbolSize":1.6759999999999997},{"id":84,"source":82,"target":84,"value":0.1409625,"lineStyle":{"width":0.431925,"color":"#f89f9a"},"symbolSize":1.409625},{"id":85,"source":82,"target":85,"value":0.11311875,"lineStyle":{"width":0.3762375,"color":"#f89f9a"},"symbolSize":1.1311875},{"id":87,"source":82,"target":87,"value":0.061024999999999996,"lineStyle":{"width":0.27205,"color":"#f89f9a"},"symbolSize":0.61025},{"id":91,"source":82,"target":91,"value":0.09593125,"lineStyle":{"width":0.34186249999999996,"color":"#f89f9a"},"symbolSize":0.9593125},{"id":105,"source":82,"target":105,"value":0.07698750000000001,"lineStyle":{"width":0.303975,"color":"#f89f9a"},"symbolSize":0.7698750000000001},{"id":128,"source":82,"target":128,"value":0.1056375,"lineStyle":{"width":0.361275,"color":"#f89f9a"},"symbolSize":1.056375},{"id":135,"source":82,"target":135,"value":0.13821250000000002,"lineStyle":{"width":0.42642500000000005,"color":"#f89f9a"},"symbolSize":1.3821250000000003},{"id":136,"source":82,"target":136,"value":0.18330000000000002,"lineStyle":{"width":0.5166000000000001,"color":"#f89f9a"},"symbolSize":1.8330000000000002},{"id":139,"source":82,"target":139,"value":0.026037499999999998,"lineStyle":{"width":0.202075,"color":"#f89f9a"},"symbolSize":0.26037499999999997}]}