{"links":[{"id":2,"source":67,"target":2,"value":0.05740625,"lineStyle":{"width":0.2648125,"color":"#f89f9a"},"symbolSize":0.5740625},{"id":5,"source":67,"target":5,"value":0.14981875000000003,"lineStyle":{"width":0.4496375,"color":"#f89f9a"},"symbolSize":1.4981875000000002},{"id":6,"source":67,"target":6,"value":0.2000875,"lineStyle":{"width":0.550175,"color":"#f89f9a"},"symbolSize":2.000875},{"id":8,"source":67,"target":8,"value":0.1949125,"lineStyle":{"width":0.539825,"color":"#f89f9a"},"symbolSize":1.949125},{"id":9,"source":67,"target":9,"value":0.14403125,"lineStyle":{"width":0.4380625,"color":"#f89f9a"},"symbolSize":1.4403125},{"id":10,"source":67,"target":10,"value":0.19229374999999999,"lineStyle":{"width":0.5345875,"color":"#f89f9a"},"symbolSize":1.9229374999999997},{"id":11,"source":67,"target":11,"value":0.206475,"lineStyle":{"width":0.56295,"color":"#f89f9a"},"symbolSize":2.06475},{"id":12,"source":67,"target":12,"value":0.24095,"lineStyle":{"width":0.6319,"color":"#f89f9a"},"symbolSize":2.4095},{"id":13,"source":67,"target":13,"value":0.18690625,"lineStyle":{"width":0.5238125,"color":"#f89f9a"},"symbolSize":1.8690625},{"id":15,"source":67,"target":15,"value":0.15733750000000002,"lineStyle":{"width":0.46467500000000006,"color":"#f89f9a"},"symbolSize":1.5733750000000002},{"id":17,"source":67,"target":17,"value":0.1265375,"lineStyle":{"width":0.40307499999999996,"color":"#f89f9a"},"symbolSize":1.265375},{"id":18,"source":67,"target":18,"value":0.137925,"lineStyle":{"width":0.42584999999999995,"color":"#f89f9a"},"symbolSize":1.3792499999999999},{"id":20,"source":67,"target":20,"value":0.16353125000000002,"lineStyle":{"width":0.47706250000000006,"color":"#f89f9a"},"symbolSize":1.6353125000000002},{"id":24,"source":67,"target":24,"value":0.17172500000000002,"lineStyle":{"width":0.49345000000000006,"color":"#f89f9a"},"symbolSize":1.7172500000000002},{"id":26,"source":67,"target":26,"value":0.1335375,"lineStyle":{"width":0.417075,"color":"#f89f9a"},"symbolSize":1.335375},{"id":27,"source":67,"target":27,"value":0.15701874999999998,"lineStyle":{"width":0.4640375,"color":"#f89f9a"},"symbolSize":1.5701874999999998},{"id":28,"source":67,"target":28,"value":0.20538125000000002,"lineStyle":{"width":0.5607625,"color":"#f89f9a"},"symbolSize":2.0538125000000003},{"id":34,"source":67,"target":34,"value":0.19451875000000002,"lineStyle":{"width":0.5390375000000001,"color":"#f89f9a"},"symbolSize":1.9451875000000003},{"id":35,"source":67,"target":35,"value":0.23849375,"lineStyle":{"width":0.6269875,"color":"#f89f9a"},"symbolSize":2.3849375},{"id":36,"source":67,"target":36,"value":0.458675,"lineStyle":{"width":1.06735,"color":"#f89f9a"},"symbolSize":4.58675},{"id":37,"source":67,"target":37,"value":0.16045625,"lineStyle":{"width":0.47091249999999996,"color":"#f89f9a"},"symbolSize":1.6045625},{"id":46,"source":67,"target":46,"value":0.09325625,"lineStyle":{"width":0.3365125,"color":"#f89f9a"},"symbolSize":0.9325625},{"id":50,"source":67,"target":50,"value":0.09815625,"lineStyle":{"width":0.3463125,"color":"#f89f9a"},"symbolSize":0.9815625},{"id":52,"source":67,"target":52,"value":0.11216249999999998,"lineStyle":{"width":0.37432499999999996,"color":"#f89f9a"},"symbolSize":1.1216249999999999},{"id":58,"source":67,"target":58,"value":0.1088375,"lineStyle":{"width":0.367675,"color":"#f89f9a"},"symbolSize":1.088375},{"id":61,"source":67,"target":61,"value":0.12405,"lineStyle":{"width":0.3981,"color":"#f89f9a"},"symbolSize":1.2405},{"id":63,"source":67,"target":63,"value":0.3326625,"lineStyle":{"width":0.8153250000000001,"color":"#f89f9a"},"symbolSize":3.3266250000000004},{"id":64,"source":67,"target":64,"value":0.2642125,"lineStyle":{"width":0.6784250000000001,"color":"#f89f9a"},"symbolSize":2.642125},{"id":66,"source":67,"target":66,"value":0.2278125,"lineStyle":{"width":0.605625,"color":"#f89f9a"},"symbolSize":2.278125},{"id":68,"source":67,"target":68,"value":0.259375,"lineStyle":{"width":0.6687500000000001,"color":"#f89f9a"},"symbolSize":2.59375},{"id":69,"source":67,"target":69,"value":0.41654375,"lineStyle":{"width":0.9830875,"color":"#f89f9a"},"symbolSize":4.1654374999999995},{"id":70,"source":67,"target":70,"value":0.45444999999999997,"lineStyle":{"width":1.0589,"color":"#f89f9a"},"symbolSize":4.544499999999999},{"id":72,"source":67,"target":72,"value":0.248425,"lineStyle":{"width":0.64685,"color":"#f89f9a"},"symbolSize":2.4842500000000003},{"id":73,"source":67,"target":73,"value":0.12800625,"lineStyle":{"width":0.4060125,"color":"#f89f9a"},"symbolSize":1.2800624999999999},{"id":75,"source":67,"target":75,"value":0.1551125,"lineStyle":{"width":0.460225,"color":"#f89f9a"},"symbolSize":1.5511249999999999},{"id":76,"source":67,"target":76,"value":0.13727499999999998,"lineStyle":{"width":0.42455,"color":"#f89f9a"},"symbolSize":1.37275},{"id":77,"source":67,"target":77,"value":0.22408750000000002,"lineStyle":{"width":0.598175,"color":"#f89f9a"},"symbolSize":2.2408750000000004},{"id":79,"source":67,"target":79,"value":0.14046874999999998,"lineStyle":{"width":0.4309375,"color":"#f89f9a"},"symbolSize":1.4046874999999996},{"id":102,"source":67,"target":102,"value":0.19440000000000002,"lineStyle":{"width":0.5388000000000001,"color":"#f89f9a"},"symbolSize":1.9440000000000002},{"id":105,"source":67,"target":105,"value":0.09410625,"lineStyle":{"width":0.3382125,"color":"#f89f9a"},"symbolSize":0.9410625},{"id":106,"source":67,"target":106,"value":0.1807375,"lineStyle":{"width":0.511475,"color":"#f89f9a"},"symbolSize":1.807375},{"id":107,"source":67,"target":107,"value":0.304525,"lineStyle":{"width":0.75905,"color":"#f89f9a"},"symbolSize":3.04525},{"id":108,"source":67,"target":108,"value":0.30596875,"lineStyle":{"width":0.7619375,"color":"#f89f9a"},"symbolSize":3.0596875},{"id":109,"source":67,"target":109,"value":0.31085624999999995,"lineStyle":{"width":0.7717124999999999,"color":"#f89f9a"},"symbolSize":3.1085624999999997},{"id":110,"source":67,"target":110,"value":0.23914375,"lineStyle":{"width":0.6282875,"color":"#f89f9a"},"symbolSize":2.3914375},{"id":111,"source":67,"target":111,"value":0.2269125,"lineStyle":{"width":0.603825,"color":"#f89f9a"},"symbolSize":2.269125},{"id":113,"source":67,"target":113,"value":0.11046249999999999,"lineStyle":{"width":0.37092499999999995,"color":"#f89f9a"},"symbolSize":1.104625},{"id":120,"source":67,"target":120,"value":0.14419375,"lineStyle":{"width":0.43838750000000004,"color":"#f89f9a"},"symbolSize":1.4419375},{"id":123,"source":67,"target":123,"value":0.0950625,"lineStyle":{"width":0.340125,"color":"#f89f9a"},"symbolSize":0.9506249999999999},{"id":142,"source":67,"target":142,"value":0.11868124999999999,"lineStyle":{"width":0.38736249999999994,"color":"#f89f9a"},"symbolSize":1.1868124999999998},{"id":143,"source":67,"target":143,"value":0.1439,"lineStyle":{"width":0.43779999999999997,"color":"#f89f9a"},"symbolSize":1.439},{"id":146,"source":67,"target":146,"value":0.0684875,"lineStyle":{"width":0.286975,"color":"#f89f9a"},"symbolSize":0.6848750000000001},{"id":150,"source":67,"target":150,"value":0.04950625,"lineStyle":{"width":0.2490125,"color":"#f89f9a"},"symbolSize":0.4950625}]}